opynfec/__init__.py
opynfec/api_wrapper.py
opynfec-0.0.4.dist-info/LICENSE
opynfec-0.0.4.dist-info/METADATA
opynfec-0.0.4.dist-info/WHEEL
opynfec-0.0.4.dist-info/top_level.txt
opynfec-0.0.4.dist-info/RECORD
